configzen/__init__.py
configzen/__main__.py
configzen/_detach.py
configzen/_setup.py
configzen/decorators.py
configzen/errors.py
configzen/field.py
configzen/interpolation.py
configzen/model.py
configzen/module.py
configzen/processor.py
configzen/py.typed
configzen/route.py
configzen/typedefs.py
configzen-0.10.0.dist-info/LICENSE
configzen-0.10.0.dist-info/METADATA
configzen-0.10.0.dist-info/WHEEL
configzen-0.10.0.dist-info/RECORD
