Metadata-Version: 2.1
Name: configzen
Version: 0.10.0
Summary: The easiest way to manage configuration files in Python
Home-page: https://github.com/bswck/configzen
License: MIT
Author: bswck
Author-email: bswck.dev@gmail.com
Requires-Python: >=3.8,<4.0
Classifier: License :: OSI Approved :: MIT License
Classifier: Programming Language :: Python :: 3
Classifier: Programming Language :: Python :: 3.8
Classifier: Programming Language :: Python :: 3.9
Classifier: Programming Language :: Python :: 3.10
Classifier: Programming Language :: Python :: 3.11
Provides-Extra: all
Provides-Extra: bson
Provides-Extra: cbor
Provides-Extra: cbor2
Provides-Extra: configobj
Provides-Extra: ion
Requires-Dist: aiofiles (>=23.1.0,<24.0.0)
Requires-Dist: anyconfig (>=0.13.0,<0.14.0)
Requires-Dist: anyconfig-bson-backend (>=0.2.0,<0.3.0) ; extra == "bson" or extra == "all"
Requires-Dist: anyconfig-cbor-backend (>=0.2.0,<0.3.0) ; extra == "cbor" or extra == "all"
Requires-Dist: anyconfig-cbor2-backend (>=0.2.0,<0.3.0) ; extra == "cbor2" or extra == "all"
Requires-Dist: anyconfig-configobj-backend (>=0.2.0,<0.3.0) ; extra == "configobj" or extra == "all"
Requires-Dist: anyconfig-ion-backend (>=0.2.0,<0.3.0) ; extra == "ion" or extra == "all"
Requires-Dist: click (>=8.1.3,<9.0.0)
Requires-Dist: pydantic (>=1.10.10,<2.0.0)
Requires-Dist: pytest (>=7.4.0,<8.0.0)
Requires-Dist: pyyaml (>=6.0,<7.0)
Requires-Dist: toml (>=0.10.2,<0.11.0)
Requires-Dist: typing-extensions (>=4.5.0,<5.0.0) ; python_version >= "3.9" and python_version < "3.11"
